hebcal/__init__.py
hebcal/calendar.py
hebcal/heb_date.py
hebcal/heb_date_old.py
hebcal/parshios.py
hebcal/scratch.py
hebcal/tests.py
hebcal/time_info.py
hebcal/zmanim.py
hebcal/pronunciation_tags/__init__.py
hebcal/pronunciation_tags/american_ashkinazik.py
hebcal/pronunciation_tags/numbers.py
hebcal/util/__init__.py
hebcal/util/location.py
hebcal/util/parse_datetime.py
hebcal/util/proccess_time.py
hebcal/util/sun.py
tests/__init__.py
tests/test_TimeInfo.py
tests/test_calendar.py
tests/test_parshios.py
tests/test_util.py
tests/test_zmanim.py
hebcal-0.0.1a0.dev4.dist-info/LICENSE
hebcal-0.0.1a0.dev4.dist-info/METADATA
hebcal-0.0.1a0.dev4.dist-info/WHEEL
hebcal-0.0.1a0.dev4.dist-info/top_level.txt
hebcal-0.0.1a0.dev4.dist-info/RECORD
