Metadata-Version: 2.1
Name: hebcal
Version: 0.0.1a0.dev4
Summary: A Python package to manipulate location aware, Hebrew dates, times, and holidays.
Home-page: https://github.com/TheBestMoshe/hebcal
Author: Moshe G
Author-email: themygcompany@gmail.com
License: UNKNOWN
Platform: UNKNOWN
Classifier: Programming Language :: Python :: 3
Classifier: License :: OSI Approved :: MIT License
Classifier: Operating System :: OS Independent
Classifier: Development Status :: 2 - Pre-Alpha
Requires-Python: >=3.6
